orchestria/__about__.py
orchestria/__init__.py
orchestria/cli.py
orchestria/settings.py
orchestria/agent/__init__.py
orchestria/agent/agent.py
orchestria/agent/cli.py
orchestria/agent/config.py
orchestria/tool/__init__.py
orchestria/tool/cli.py
orchestria/tool/config.py
orchestria/tool/tool.py
orchestria-0.0.2.dist-info/METADATA
orchestria-0.0.2.dist-info/WHEEL
orchestria-0.0.2.dist-info/entry_points.txt
orchestria-0.0.2.dist-info/licenses/LICENSE.txt
orchestria-0.0.2.dist-info/RECORD
